bgu-aws-utils/__init__.py
bgu-aws-utils/launch_aws.py
bgu-aws-utils/manage_instance.py
bgu_aws/__init__.py
bgu_aws/launch_aws.py
bgu_aws/manage_instance.py
bgu_aws-0.0.4.dist-info/METADATA
bgu_aws-0.0.4.dist-info/RECORD
bgu_aws-0.0.4.dist-info/WHEEL
bgu_aws-0.0.4.dist-info/top_level.txt
bgu_aws_utils/__init__.py
bgu_aws_utils/launch_aws.py
bgu_aws_utils/manage_instance.py
