Metadata-Version: 2.1
Name: bgu-aws
Version: 0.0.4
Summary: Utilities for AWS code managements
Home-page: https://https://github.com/arbellea/bgu-aws-utils
Author: Assaf Arbelle
Author-email: arbellea@post.bgu.ac.il
License: UNKNOWN
Platform: UNKNOWN
Classifier: Programming Language :: Python :: 3
Classifier: License :: OSI Approved :: MIT License
Classifier: Operating System :: OS Independent
Requires-Python: >=3.5
Requires-Dist: requests
